README.md
pyproject.toml
trustgraph/__init__.py
trustgraph/flow_version.py
trustgraph/agent/__init__.py
trustgraph/agent/tool_filter.py
trustgraph/agent/mcp_tool/__init__.py
trustgraph/agent/mcp_tool/__main__.py
trustgraph/agent/mcp_tool/service.py
trustgraph/agent/react/__init__.py
trustgraph/agent/react/__main__.py
trustgraph/agent/react/agent_manager.py
trustgraph/agent/react/service.py
trustgraph/agent/react/streaming_parser.py
trustgraph/agent/react/tools.py
trustgraph/agent/react/types.py
trustgraph/chunking/__init__.py
trustgraph/chunking/recursive/__init__.py
trustgraph/chunking/recursive/__main__.py
trustgraph/chunking/recursive/chunker.py
trustgraph/chunking/token/__init__.py
trustgraph/chunking/token/__main__.py
trustgraph/chunking/token/chunker.py
trustgraph/config/service/__init__.py
trustgraph/config/service/__main__.py
trustgraph/config/service/config.py
trustgraph/config/service/flow.py
trustgraph/config/service/service.py
trustgraph/cores/__init__.py
trustgraph/cores/__main__.py
trustgraph/cores/knowledge.py
trustgraph/cores/service.py
trustgraph/decoding/__init__.py
trustgraph/decoding/mistral_ocr/__init__.py
trustgraph/decoding/mistral_ocr/__main__.py
trustgraph/decoding/mistral_ocr/processor.py
trustgraph/decoding/pdf/__init__.py
trustgraph/decoding/pdf/__main__.py
trustgraph/decoding/pdf/pdf_decoder.py
trustgraph/direct/__init__.py
trustgraph/direct/cassandra_kg.py
trustgraph/direct/milvus_doc_embeddings.py
trustgraph/direct/milvus_graph_embeddings.py
trustgraph/embeddings/__init__.py
trustgraph/embeddings/document_embeddings/__init__.py
trustgraph/embeddings/document_embeddings/__main__.py
trustgraph/embeddings/document_embeddings/embeddings.py
trustgraph/embeddings/fastembed/__init__.py
trustgraph/embeddings/fastembed/__main__.py
trustgraph/embeddings/fastembed/processor.py
trustgraph/embeddings/graph_embeddings/__init__.py
trustgraph/embeddings/graph_embeddings/__main__.py
trustgraph/embeddings/graph_embeddings/embeddings.py
trustgraph_flow.egg-info/PKG-INFO
trustgraph_flow.egg-info/SOURCES.txt
trustgraph_flow.egg-info/dependency_links.txt
trustgraph_flow.egg-info/entry_points.txt
trustgraph_flow.egg-info/requires.txt
trustgraph_flow.egg-info/top_level.txt