Metadata-Version: 2.4
Name: trustgraph-flow
Version: 1.8.2
Summary: TrustGraph provides a means to run a pipeline of flexible AI processing components in a flexible means to achieve a processing pipeline.
Author-email: "trustgraph.ai" <security@trustgraph.ai>
Project-URL: Homepage, https://github.com/trustgraph-ai/trustgraph
Classifier: Programming Language :: Python :: 3
Classifier: Operating System :: OS Independent
Requires-Python: >=3.8
Requires-Dist: trustgraph-base<1.9,>=1.8
Requires-Dist: aiohttp
Requires-Dist: anthropic
Requires-Dist: scylla-driver
Requires-Dist: cohere
Requires-Dist: cryptography
Requires-Dist: faiss-cpu
Requires-Dist: falkordb
Requires-Dist: fastembed
Requires-Dist: google-genai
Requires-Dist: ibis
Requires-Dist: jsonschema
Requires-Dist: langchain
Requires-Dist: langchain-community
Requires-Dist: langchain-core
Requires-Dist: langchain-text-splitters
Requires-Dist: mcp
Requires-Dist: minio
Requires-Dist: mistralai
Requires-Dist: neo4j
Requires-Dist: nltk
Requires-Dist: ollama
Requires-Dist: openai
Requires-Dist: pinecone[grpc]
Requires-Dist: prometheus-client
Requires-Dist: pulsar-client
Requires-Dist: pymilvus
Requires-Dist: pypdf
Requires-Dist: pyyaml
Requires-Dist: qdrant-client
Requires-Dist: rdflib
Requires-Dist: requests
Requires-Dist: strawberry-graphql
Requires-Dist: tabulate
Requires-Dist: tiktoken
Requires-Dist: urllib3
